fediverser/admin/__init__.py
fediverser/admin/asgi.py
fediverser/admin/celery.py
fediverser/admin/database_router.py
fediverser/admin/settings.py
fediverser/admin/urls.py
fediverser/admin/wsgi.py
fediverser/apps/core/__init__.py
fediverser/apps/core/admin.py
fediverser/apps/core/apps.py
fediverser/apps/core/management/commands/get_new_reddit_posts.py
fediverser/apps/core/migrations/0001_initial.py
fediverser/apps/core/migrations/__init__.py
fediverser/apps/core/models.py
fediverser/apps/core/tests.py
fediverser/apps/core/views.py
fediverser/apps/lemmy/__init__.py
fediverser/apps/lemmy/admin.py
fediverser/apps/lemmy/apps.py
fediverser/apps/lemmy/handlers.py
fediverser/apps/lemmy/management/commands/mirror_reddit.py
fediverser/apps/lemmy/migrations/0001_initial.py
fediverser/apps/lemmy/migrations/__init__.py
fediverser/apps/lemmy/models.py
fediverser/apps/lemmy/tests.py
fediverser/apps/lemmy/views.py
fediverser-0.2.0.dist-info/LICENSE
fediverser-0.2.0.dist-info/METADATA
fediverser-0.2.0.dist-info/WHEEL
fediverser-0.2.0.dist-info/entry_points.txt
fediverser-0.2.0.dist-info/RECORD
